Metadata-Version: 2.1
Name: FederatedLib
Version: 0.1.0
Summary: Librairie pour faire du federated learning
Author: Logan Bauvois, Anthony Carvalho
Requires-Python: >=3.6.9
Requires-Dist: torch
Requires-Dist: torchvision
Requires-Dist: paramiko
Requires-Dist: matplotlib
Requires-Dist: numpy
Requires-Dist: setuptools
Requires-Dist: pandas
